{
	"Id": "Lootable_00171",
	"IsStatic": true,
	"useGravity": true,
	"randomRotation": false,
	"Position": {
		"x": 0,
		"y": 0,
		"z": 0
	},
	"Rotation": {
		"x": 0,
		"y": 0,
		"z": 0
	},
	"IsGroupPosition": false,
	"GroupPositions": [],
	"Root": "5e0675faf15d9d2288415296",
	"Items": [
		{
			"_id": "5e0675faf15d9d2288415296",
			"_tpl": "5909d5ef86f77467974efbd8"
		},
		{
			"_id": "5e0675faf15d9d2288415297",
			"_tpl": "59db3acc86f7742a2c4ab912",
			"parentId": "5e0675faf15d9d2288415296",
			"slotId": "main",
			"location": {
				"x": 0,
				"y": 0,
				"r": 0
			}
		}
	]
}