{
	"Id": "Lootable_00131",
	"IsStatic": true,
	"useGravity": true,
	"randomRotation": false,
	"Position": {
		"x": 0,
		"y": 0,
		"z": 0
	},
	"Rotation": {
		"x": 0,
		"y": 0,
		"z": 0
	},
	"IsGroupPosition": false,
	"GroupPositions": [],
	"Root": "5e0675d5f15d9d2288414f2d",
	"Items": [
		{
			"_id": "5e0675d5f15d9d2288414f2d",
			"_tpl": "5ad74cf586f774391278f6f0"
		},
		{
			"_id": "5e0675d5f15d9d2288414f2e",
			"_tpl": "5449016a4bdc2d6f028b456f",
			"parentId": "5e0675d5f15d9d2288414f2d",
			"slotId": "main",
			"location": {
				"x": 0,
				"y": 0,
				"r": 0
			},
			"upd": {
				"StackObjectsCount": 870
			}
		},
		{
			"_id": "5e0675d5f15d9d2288414f2f",
			"_tpl": "5449016a4bdc2d6f028b456f",
			"parentId": "5e0675d5f15d9d2288414f2d",
			"slotId": "main",
			"location": {
				"x": 1,
				"y": 0,
				"r": 0
			},
			"upd": {
				"StackObjectsCount": 868
			}
		},
		{
			"_id": "5e0675d5f15d9d2288414f30",
			"_tpl": "5449016a4bdc2d6f028b456f",
			"parentId": "5e0675d5f15d9d2288414f2d",
			"slotId": "main",
			"location": {
				"x": 0,
				"y": 1,
				"r": 0
			},
			"upd": {
				"StackObjectsCount": 762
			}
		},
		{
			"_id": "5e0675d5f15d9d2288414f31",
			"_tpl": "5449016a4bdc2d6f028b456f",
			"parentId": "5e0675d5f15d9d2288414f2d",
			"slotId": "main",
			"location": {
				"x": 1,
				"y": 1,
				"r": 0
			},
			"upd": {
				"StackObjectsCount": 1024
			}
		}
	]
}