{
	"Id": "Lootable_00204",
	"IsStatic": true,
	"useGravity": true,
	"randomRotation": false,
	"Position": {
		"x": 0,
		"y": 0,
		"z": 0
	},
	"Rotation": {
		"x": 0,
		"y": 0,
		"z": 0
	},
	"IsGroupPosition": false,
	"GroupPositions": [],
	"Root": "5d31e3e7645bb732ce6f1988",
	"Items": [
		{
			"_id": "5d31e3e7645bb732ce6f1988",
			"_tpl": "5909d24f86f77466f56e6855"
		},
		{
			"_id": "5d31e3e7645bb732ce6f1989",
			"_tpl": "544fb45d4bdc2dee738b4568",
			"parentId": "5d31e3e7645bb732ce6f1988",
			"slotId": "main",
			"location": {
				"x": 0,
				"y": 0,
				"r": 0
			}
		},
		{
			"_id": "5d31e3e7645bb732ce6f198a",
			"_tpl": "5b4335ba86f7744d2837a264",
			"parentId": "5d31e3e7645bb732ce6f1988",
			"slotId": "main",
			"location": {
				"x": 1,
				"y": 0,
				"r": 0
			}
		},
		{
			"_id": "5d31e3e7645bb732ce6f198b",
			"_tpl": "5751a25924597722c463c472",
			"parentId": "5d31e3e7645bb732ce6f1988",
			"slotId": "main",
			"location": {
				"x": 2,
				"y": 0,
				"r": 0
			}
		}
	]
}