{
	"Id": "Lootable_00332",
	"IsStatic": true,
	"useGravity": true,
	"randomRotation": false,
	"Position": {
		"x": 0,
		"y": 0,
		"z": 0
	},
	"Rotation": {
		"x": 0,
		"y": 0,
		"z": 0
	},
	"IsGroupPosition": false,
	"GroupPositions": [],
	"Root": "5db5d05df113b904523ad4ab",
	"Items": [
		{
			"_id": "5db5d05df113b904523ad4ab",
			"_tpl": "5ad74cf586f774391278f6f0"
		},
		{
			"_id": "5db5d05df113b904523ad4ac",
			"_tpl": "5449016a4bdc2d6f028b456f",
			"parentId": "5db5d05df113b904523ad4ab",
			"slotId": "main",
			"location": {
				"x": 0,
				"y": 0,
				"r": 0
			},
			"upd": {
				"StackObjectsCount": 854
			}
		},
		{
			"_id": "5db5d05df113b904523ad4ad",
			"_tpl": "5449016a4bdc2d6f028b456f",
			"parentId": "5db5d05df113b904523ad4ab",
			"slotId": "main",
			"location": {
				"x": 1,
				"y": 0,
				"r": 0
			},
			"upd": {
				"StackObjectsCount": 820
			}
		},
		{
			"_id": "5db5d05df113b904523ad4ae",
			"_tpl": "5449016a4bdc2d6f028b456f",
			"parentId": "5db5d05df113b904523ad4ab",
			"slotId": "main",
			"location": {
				"x": 0,
				"y": 1,
				"r": 0
			},
			"upd": {
				"StackObjectsCount": 955
			}
		},
		{
			"_id": "5db5d05df113b904523ad4af",
			"_tpl": "5449016a4bdc2d6f028b456f",
			"parentId": "5db5d05df113b904523ad4ab",
			"slotId": "main",
			"location": {
				"x": 1,
				"y": 1,
				"r": 0
			},
			"upd": {
				"StackObjectsCount": 874
			}
		}
	]
}