{
	"Id": "Lootable_00312",
	"IsStatic": true,
	"useGravity": true,
	"randomRotation": false,
	"Position": {
		"x": 0,
		"y": 0,
		"z": 0
	},
	"Rotation": {
		"x": 0,
		"y": 0,
		"z": 0
	},
	"IsGroupPosition": false,
	"GroupPositions": [],
	"Root": "5e0675da26f42d2de93ffcac",
	"Items": [
		{
			"_id": "5e0675da26f42d2de93ffcac",
			"_tpl": "578f87a3245977356274f2cb"
		},
		{
			"_id": "5e0675da26f42d2de93ffcad",
			"_tpl": "544fb45d4bdc2dee738b4568",
			"parentId": "5e0675da26f42d2de93ffcac",
			"slotId": "main",
			"location": {
				"x": 0,
				"y": 0,
				"r": 0
			}
		},
		{
			"_id": "5e0675da26f42d2de93ffcae",
			"_tpl": "590c5a7286f7747884343aea",
			"parentId": "5e0675da26f42d2de93ffcac",
			"slotId": "main",
			"location": {
				"x": 1,
				"y": 0,
				"r": 0
			}
		},
		{
			"_id": "5e0675da26f42d2de93ffcaf",
			"_tpl": "5d1b3f2d86f774253763b735",
			"parentId": "5e0675da26f42d2de93ffcac",
			"slotId": "main",
			"location": {
				"x": 2,
				"y": 0,
				"r": 0
			}
		},
		{
			"_id": "5e0675da26f42d2de93ffcb0",
			"_tpl": "5d6fc87386f77449db3db94e",
			"parentId": "5e0675da26f42d2de93ffcac",
			"slotId": "main",
			"location": {
				"x": 3,
				"y": 0,
				"r": 0
			}
		}
	]
}