{
	"Id": "Lootable_00299",
	"IsStatic": true,
	"useGravity": true,
	"randomRotation": false,
	"Position": {
		"x": 0,
		"y": 0,
		"z": 0
	},
	"Rotation": {
		"x": 0,
		"y": 0,
		"z": 0
	},
	"IsGroupPosition": false,
	"GroupPositions": [],
	"Root": "5db5d031cd1e3d3a9450753c",
	"Items": [
		{
			"_id": "5db5d031cd1e3d3a9450753c",
			"_tpl": "5909d76c86f77471e53d2adf"
		},
		{
			"_id": "5db5d031cd1e3d3a9450753d",
			"_tpl": "5649af884bdc2d1b2b8b4589",
			"parentId": "5db5d031cd1e3d3a9450753c",
			"slotId": "main",
			"location": {
				"x": 0,
				"y": 0,
				"r": 0
			}
		},
		{
			"_id": "5db5d031cd1e3d3a9450753e",
			"_tpl": "56def37dd2720bec348b456a",
			"parentId": "5db5d031cd1e3d3a9450753c",
			"slotId": "main",
			"location": {
				"x": 2,
				"y": 0,
				"r": 0
			}
		},
		{
			"_id": "5db5d031cd1e3d3a9450753f",
			"_tpl": "5a800961159bd4315e3a1657",
			"parentId": "5db5d031cd1e3d3a9450753c",
			"slotId": "main",
			"location": {
				"x": 3,
				"y": 0,
				"r": 0
			}
		}
	]
}