{
	"Id": "Lootable_00093",
	"IsStatic": true,
	"useGravity": true,
	"randomRotation": false,
	"Position": {
		"x": 0,
		"y": 0,
		"z": 0
	},
	"Rotation": {
		"x": 0,
		"y": 0,
		"z": 0
	},
	"IsGroupPosition": false,
	"GroupPositions": [],
	"Root": "5d31e3bf645bb766be6608ee",
	"Items": [
		{
			"_id": "5d31e3bf645bb766be6608ee",
			"_tpl": "59139c2186f77411564f8e42"
		},
		{
			"_id": "5d31e3bf645bb766be6608ef",
			"_tpl": "5c06779c86f77426e00dd782",
			"parentId": "5d31e3bf645bb766be6608ee",
			"slotId": "main",
			"location": {
				"x": 0,
				"y": 0,
				"r": 0
			}
		}
	]
}