{
	"Id": "loot_mix_food_med_ammo (129)4935130",
	"IsStatic": false,
	"useGravity": true,
	"randomRotation": true,
	"Position": {
		"x": 43.6634521,
		"y": 22.2108116,
		"z": -282.167358
	},
	"Rotation": {
		"x": 0,
		"y": 0,
		"z": 0
	},
	"IsGroupPosition": false,
	"GroupPositions": [],
	"Root": "5d31e3b9645bb766be66035d",
	"Items": [
		{
			"_id": "5d31e3b9645bb766be66035d",
			"_tpl": "5737330a2459776af32363a1"
		},
		{
			"_id": "5d31e3b9645bb766be66035e",
			"_tpl": "56dff0bed2720bb0668b4567",
			"parentId": "5d31e3b9645bb766be66035d",
			"slotId": "cartridges",
			"upd": {
				"StackObjectsCount": 30
			}
		}
	]
}