{
	"Id": "Lootable_00179",
	"IsStatic": true,
	"useGravity": true,
	"randomRotation": false,
	"Position": {
		"x": 0,
		"y": 0,
		"z": 0
	},
	"Rotation": {
		"x": 0,
		"y": 0,
		"z": 0
	},
	"IsGroupPosition": false,
	"GroupPositions": [],
	"Root": "5d31e3be645bb766be6604fd",
	"Items": [
		{
			"_id": "5d31e3be645bb766be6604fd",
			"_tpl": "578f8778245977358849a9b5"
		},
		{
			"_id": "5d31e3be645bb766be6604fe",
			"_tpl": "573476d324597737da2adc13",
			"parentId": "5d31e3be645bb766be6604fd",
			"slotId": "main",
			"location": {
				"x": 0,
				"y": 0,
				"r": 0
			}
		},
		{
			"_id": "5d31e3be645bb766be6604ff",
			"_tpl": "57347b8b24597737dd42e192",
			"parentId": "5d31e3be645bb766be6604fd",
			"slotId": "main",
			"location": {
				"x": 1,
				"y": 0,
				"r": 0
			}
		},
		{
			"_id": "5d31e3be645bb766be660500",
			"_tpl": "5449016a4bdc2d6f028b456f",
			"parentId": "5d31e3be645bb766be6604fd",
			"slotId": "main",
			"location": {
				"x": 0,
				"y": 1,
				"r": 0
			},
			"upd": {
				"StackObjectsCount": 835
			}
		}
	]
}