{
	"Id": "loot_ammo (104)5868922",
	"IsStatic": false,
	"useGravity": true,
	"randomRotation": true,
	"Position": {
		"x": -15.9526367,
		"y": 28.0158119,
		"z": -240.1123
	},
	"Rotation": {
		"x": 0,
		"y": 0,
		"z": 0
	},
	"IsGroupPosition": false,
	"GroupPositions": [],
	"Root": "5e0675cd243fd85e273fdf58",
	"Items": [
		{
			"_id": "5e0675cd243fd85e273fdf58",
			"_tpl": "573722e82459776104581c21"
		},
		{
			"_id": "5e0675cd243fd85e273fdf59",
			"_tpl": "573718ba2459775a75491131",
			"parentId": "5e0675cd243fd85e273fdf58",
			"slotId": "cartridges",
			"upd": {
				"StackObjectsCount": 16
			}
		}
	]
}