{
	"Id": "loot_mods (111)4941006",
	"IsStatic": false,
	"useGravity": true,
	"randomRotation": true,
	"Position": {
		"x": -15.2675781,
		"y": 28.11481,
		"z": -32.19934
	},
	"Rotation": {
		"x": 0,
		"y": 0,
		"z": 0
	},
	"IsGroupPosition": false,
	"GroupPositions": [],
	"Root": "5d31e3e3645bb732ce6f17ef",
	"Items": [
		{
			"_id": "5d31e3e3645bb732ce6f17ef",
			"_tpl": "59fafc9386f774067d462453"
		},
		{
			"_id": "5d31e3e3645bb732ce6f17f0",
			"_tpl": "59e655cb86f77411dc52a77b",
			"parentId": "5d31e3e3645bb732ce6f17ef",
			"slotId": "cartridges",
			"upd": {
				"StackObjectsCount": 7
			}
		}
	]
}