{
	"Id": "Lootable_00205",
	"IsStatic": true,
	"useGravity": true,
	"randomRotation": false,
	"Position": {
		"x": 0,
		"y": 0,
		"z": 0
	},
	"Rotation": {
		"x": 0,
		"y": 0,
		"z": 0
	},
	"IsGroupPosition": false,
	"GroupPositions": [],
	"Root": "5e0675dd9a5d683c327ed503",
	"Items": [
		{
			"_id": "5e0675dd9a5d683c327ed503",
			"_tpl": "578f87a3245977356274f2cb"
		},
		{
			"_id": "5e0675dd9a5d683c327ed504",
			"_tpl": "59e35abd86f7741778269d82",
			"parentId": "5e0675dd9a5d683c327ed503",
			"slotId": "main",
			"location": {
				"x": 0,
				"y": 0,
				"r": 0
			}
		},
		{
			"_id": "5e0675dd9a5d683c327ed505",
			"_tpl": "5d1b313086f77425227d1678",
			"parentId": "5e0675dd9a5d683c327ed503",
			"slotId": "main",
			"location": {
				"x": 1,
				"y": 0,
				"r": 0
			}
		}
	]
}