{
	"Id": "Lootable_00314",
	"IsStatic": true,
	"useGravity": true,
	"randomRotation": false,
	"Position": {
		"x": 0,
		"y": 0,
		"z": 0
	},
	"Rotation": {
		"x": 0,
		"y": 0,
		"z": 0
	},
	"IsGroupPosition": false,
	"GroupPositions": [],
	"Root": "5e0675db26f42d2de93ffd50",
	"Items": [
		{
			"_id": "5e0675db26f42d2de93ffd50",
			"_tpl": "578f87a3245977356274f2cb"
		},
		{
			"_id": "5e0675db26f42d2de93ffd51",
			"_tpl": "57347da92459774491567cf5",
			"parentId": "5e0675db26f42d2de93ffd50",
			"slotId": "main",
			"location": {
				"x": 0,
				"y": 0,
				"r": 0
			}
		},
		{
			"_id": "5e0675db26f42d2de93ffd52",
			"_tpl": "57513f9324597720a7128161",
			"parentId": "5e0675db26f42d2de93ffd50",
			"slotId": "main",
			"location": {
				"x": 1,
				"y": 0,
				"r": 0
			}
		},
		{
			"_id": "5e0675db26f42d2de93ffd53",
			"_tpl": "57347c1124597737fb1379e3",
			"parentId": "5e0675db26f42d2de93ffd50",
			"slotId": "main",
			"location": {
				"x": 2,
				"y": 0,
				"r": 0
			}
		},
		{
			"_id": "5e0675db26f42d2de93ffd54",
			"_tpl": "573475fb24597737fb1379e1",
			"parentId": "5e0675db26f42d2de93ffd50",
			"slotId": "main",
			"location": {
				"x": 3,
				"y": 0,
				"r": 0
			}
		}
	]
}