{
	"Id": "Lootable_00166",
	"IsStatic": true,
	"useGravity": true,
	"randomRotation": false,
	"Position": {
		"x": 0,
		"y": 0,
		"z": 0
	},
	"Rotation": {
		"x": 0,
		"y": 0,
		"z": 0
	},
	"IsGroupPosition": false,
	"GroupPositions": [],
	"Root": "5e3829e8f470ac6fd82e6bca",
	"Items": [
		{
			"_id": "5e3829e8f470ac6fd82e6bca",
			"_tpl": "578f87b7245977356274f2cd"
		},
		{
			"_id": "5e3829e8f470ac6fd82e6bcb",
			"_tpl": "573478bc24597738002c6175",
			"parentId": "5e3829e8f470ac6fd82e6bca",
			"slotId": "main",
			"location": {
				"x": 0,
				"y": 0,
				"r": 0
			}
		},
		{
			"_id": "5e3829e8f470ac6fd82e6bcc",
			"_tpl": "5734795124597738002c6176",
			"parentId": "5e3829e8f470ac6fd82e6bca",
			"slotId": "main",
			"location": {
				"x": 1,
				"y": 0,
				"r": 0
			}
		}
	]
}