{
	"Id": "GunsafeSpawn 1 (4)(Clone)4378476",
	"IsStatic": false,
	"useGravity": true,
	"randomRotation": false,
	"Position": {
		"x": -286.86908,
		"y": 0.332058668,
		"z": -85.36989
	},
	"Rotation": {
		"x": 271.894043,
		"y": -0.0002582919,
		"z": 91.16332
	},
	"IsGroupPosition": false,
	"GroupPositions": [],
	"Root": "5e3829f37e788532af35f83a",
	"Items": [
		{
			"_id": "5e3829f37e788532af35f83a",
			"_tpl": "5739d41224597779c3645501"
		},
		{
			"_id": "5e3829f37e788532af35f83b",
			"_tpl": "56d59d3ad2720bdb418b4577",
			"parentId": "5e3829f37e788532af35f83a",
			"slotId": "cartridges",
			"upd": {
				"StackObjectsCount": 16
			}
		}
	]
}