{
	"Id": "Lootable_00383",
	"IsStatic": true,
	"useGravity": true,
	"randomRotation": false,
	"Position": {
		"x": 0,
		"y": 0,
		"z": 0
	},
	"Rotation": {
		"x": 0,
		"y": 0,
		"z": 0
	},
	"IsGroupPosition": false,
	"GroupPositions": [],
	"Root": "5e382a1968b10c71c3112e10",
	"Items": [
		{
			"_id": "5e382a1968b10c71c3112e10",
			"_tpl": "5909d76c86f77471e53d2adf"
		},
		{
			"_id": "5e382a1968b10c71c3112e11",
			"_tpl": "57ffaea724597779f52b3a4d",
			"parentId": "5e382a1968b10c71c3112e10",
			"slotId": "main",
			"location": {
				"x": 0,
				"y": 0,
				"r": 0
			}
		},
		{
			"_id": "5e382a1968b10c71c3112e12",
			"_tpl": "57c55f112459772d28133310",
			"parentId": "5e382a1968b10c71c3112e10",
			"slotId": "main",
			"location": {
				"x": 1,
				"y": 0,
				"r": 0
			}
		},
		{
			"_id": "5e382a1968b10c71c3112e13",
			"_tpl": "5448c12b4bdc2d02308b456f",
			"parentId": "5e382a1968b10c71c3112e10",
			"slotId": "main",
			"location": {
				"x": 2,
				"y": 0,
				"r": 0
			}
		}
	]
}