{
	"Id": "Lootable_00001",
	"IsStatic": true,
	"useGravity": true,
	"randomRotation": false,
	"Position": {
		"x": 0,
		"y": 0,
		"z": 0
	},
	"Rotation": {
		"x": 0,
		"y": 0,
		"z": 0
	},
	"IsGroupPosition": false,
	"GroupPositions": [],
	"Root": "5e3829f67e788532af35fc43",
	"Items": [
		{
			"_id": "5e3829f67e788532af35fc43",
			"_tpl": "5909d89086f77472591234a0"
		},
		{
			"_id": "5e3829f67e788532af35fc44",
			"_tpl": "59fc48e086f77463b1118392",
			"parentId": "5e3829f67e788532af35fc43",
			"slotId": "main",
			"location": {
				"x": 0,
				"y": 0,
				"r": 0
			}
		},
		{
			"_id": "5e3829f67e788532af35fc45",
			"_tpl": "57dbb57e2459774673234890",
			"parentId": "5e3829f67e788532af35fc43",
			"slotId": "main",
			"location": {
				"x": 1,
				"y": 0,
				"r": 0
			}
		},
		{
			"_id": "5e3829f67e788532af35fc46",
			"_tpl": "5d120a10d7ad1a4e1026ba85",
			"parentId": "5e3829f67e788532af35fc43",
			"slotId": "main",
			"location": {
				"x": 3,
				"y": 0,
				"r": 0
			}
		}
	]
}