{
	"Id": "Lootable_00197",
	"IsStatic": true,
	"useGravity": true,
	"randomRotation": false,
	"Position": {
		"x": 0,
		"y": 0,
		"z": 0
	},
	"Rotation": {
		"x": 0,
		"y": 0,
		"z": 0
	},
	"IsGroupPosition": false,
	"GroupPositions": [],
	"Root": "5e3829ff1d55576e1a527045",
	"Items": [
		{
			"_id": "5e3829ff1d55576e1a527045",
			"_tpl": "5d6d2bb386f774785b07a77a"
		},
		{
			"_id": "5e3829ff1d55576e1a527046",
			"_tpl": "544fb45d4bdc2dee738b4568",
			"parentId": "5e3829ff1d55576e1a527045",
			"slotId": "main",
			"location": {
				"x": 0,
				"y": 0,
				"r": 0
			}
		},
		{
			"_id": "5e3829ff1d55576e1a527047",
			"_tpl": "590a3cd386f77436f20848cb",
			"parentId": "5e3829ff1d55576e1a527045",
			"slotId": "main",
			"location": {
				"x": 1,
				"y": 0,
				"r": 0
			}
		},
		{
			"_id": "5e3829ff1d55576e1a527048",
			"_tpl": "5449016a4bdc2d6f028b456f",
			"parentId": "5e3829ff1d55576e1a527045",
			"slotId": "main",
			"location": {
				"x": 2,
				"y": 0,
				"r": 0
			},
			"upd": {
				"StackObjectsCount": 1110
			}
		}
	]
}