{
	"Id": "Lootable_00005",
	"IsStatic": true,
	"useGravity": true,
	"randomRotation": false,
	"Position": {
		"x": 0,
		"y": 0,
		"z": 0
	},
	"Rotation": {
		"x": 0,
		"y": 0,
		"z": 0
	},
	"IsGroupPosition": false,
	"GroupPositions": [],
	"Root": "5e3829d91d55576e1a52666d",
	"Items": [
		{
			"_id": "5e3829d91d55576e1a52666d",
			"_tpl": "5909e4b686f7747f5b744fa4"
		},
		{
			"_id": "5e3829d91d55576e1a52666e",
			"_tpl": "590a3cd386f77436f20848cb",
			"parentId": "5e3829d91d55576e1a52666d",
			"slotId": "main",
			"location": {
				"x": 0,
				"y": 0,
				"r": 0
			}
		}
	]
}