{
	"Id": "Lootable_00012",
	"IsStatic": true,
	"useGravity": true,
	"randomRotation": false,
	"Position": {
		"x": 0,
		"y": 0,
		"z": 0
	},
	"Rotation": {
		"x": 0,
		"y": 0,
		"z": 0
	},
	"IsGroupPosition": false,
	"GroupPositions": [],
	"Root": "5e382a011d55576e1a5271dc",
	"Items": [
		{
			"_id": "5e382a011d55576e1a5271dc",
			"_tpl": "5909d45286f77465a8136dc6"
		},
		{
			"_id": "5e382a011d55576e1a5271dd",
			"_tpl": "56dff421d2720b5f5a8b4567",
			"parentId": "5e382a011d55576e1a5271dc",
			"slotId": "main",
			"location": {
				"x": 0,
				"y": 0,
				"r": 0
			},
			"upd": {
				"StackObjectsCount": 11
			}
		}
	]
}