{
	"Id": "Lootable_00382",
	"IsStatic": true,
	"useGravity": true,
	"randomRotation": false,
	"Position": {
		"x": 0,
		"y": 0,
		"z": 0
	},
	"Rotation": {
		"x": 0,
		"y": 0,
		"z": 0
	},
	"IsGroupPosition": false,
	"GroupPositions": [],
	"Root": "5e382a2568b10c71c3113697",
	"Items": [
		{
			"_id": "5e382a2568b10c71c3113697",
			"_tpl": "5909d50c86f774659e6aaebe"
		},
		{
			"_id": "5e382a2568b10c71c3113698",
			"_tpl": "57347c77245977448d35f6e2",
			"parentId": "5e382a2568b10c71c3113697",
			"slotId": "main",
			"location": {
				"x": 0,
				"y": 0,
				"r": 0
			}
		},
		{
			"_id": "5e382a2568b10c71c3113699",
			"_tpl": "5672cb304bdc2dc2088b456a",
			"parentId": "5e382a2568b10c71c3113697",
			"slotId": "main",
			"location": {
				"x": 1,
				"y": 0,
				"r": 0
			}
		},
		{
			"_id": "5e382a2568b10c71c311369a",
			"_tpl": "5d1b39a386f774252339976f",
			"parentId": "5e382a2568b10c71c3113697",
			"slotId": "main",
			"location": {
				"x": 2,
				"y": 0,
				"r": 0
			}
		},
		{
			"_id": "5e382a2568b10c71c311369b",
			"_tpl": "57347cd0245977445a2d6ff1",
			"parentId": "5e382a2568b10c71c3113697",
			"slotId": "main",
			"location": {
				"x": 3,
				"y": 0,
				"r": 0
			}
		}
	]
}