{
	"Id": "loot_rf_ammo_true (102)3925964",
	"IsStatic": false,
	"useGravity": true,
	"randomRotation": true,
	"Position": {
		"x": 106.012024,
		"y": -6.208,
		"z": 52.03601
	},
	"Rotation": {
		"x": 0,
		"y": 0,
		"z": 0
	},
	"IsGroupPosition": false,
	"GroupPositions": [],
	"Root": "5e382a0468b10c71c31122a8",
	"Items": [
		{
			"_id": "5e382a0468b10c71c31122a8",
			"_tpl": "57372e4a24597768553071c2"
		},
		{
			"_id": "5e382a0468b10c71c31122a9",
			"_tpl": "56dff338d2720bbd668b4569",
			"parentId": "5e382a0468b10c71c31122a8",
			"slotId": "cartridges",
			"upd": {
				"StackObjectsCount": 30
			}
		}
	]
}