{
	"Id": "Lootable_00095",
	"IsStatic": true,
	"useGravity": true,
	"randomRotation": false,
	"Position": {
		"x": 0,
		"y": 0,
		"z": 0
	},
	"Rotation": {
		"x": 0,
		"y": 0,
		"z": 0
	},
	"IsGroupPosition": false,
	"GroupPositions": [],
	"Root": "5e3829fd2855471525603033",
	"Items": [
		{
			"_id": "5e3829fd2855471525603033",
			"_tpl": "578f87b7245977356274f2cd"
		},
		{
			"_id": "5e3829fd2855471525603034",
			"_tpl": "5780cf9e2459777df90dcb73",
			"parentId": "5e3829fd2855471525603033",
			"slotId": "main",
			"location": {
				"x": 0,
				"y": 0,
				"r": 0
			}
		},
		{
			"_id": "5e3829fd2855471525603035",
			"_tpl": "56742c284bdc2d98058b456d",
			"parentId": "5e3829fd2855471525603033",
			"slotId": "main",
			"location": {
				"x": 1,
				"y": 0,
				"r": 0
			}
		}
	]
}