{
	"Id": "Lootable_00355",
	"IsStatic": true,
	"useGravity": true,
	"randomRotation": false,
	"Position": {
		"x": 0,
		"y": 0,
		"z": 0
	},
	"Rotation": {
		"x": 0,
		"y": 0,
		"z": 0
	},
	"IsGroupPosition": false,
	"GroupPositions": [],
	"Root": "5e3829fa2855471525602c92",
	"Items": [
		{
			"_id": "5e3829fa2855471525602c92",
			"_tpl": "578f87a3245977356274f2cb"
		},
		{
			"_id": "5e3829fa2855471525602c93",
			"_tpl": "5b43575a86f77424f443fe62",
			"parentId": "5e3829fa2855471525602c92",
			"slotId": "main",
			"location": {
				"x": 0,
				"y": 0,
				"r": 0
			}
		},
		{
			"_id": "5e3829fa2855471525602c94",
			"_tpl": "5d1c819a86f774771b0acd6c",
			"parentId": "5e3829fa2855471525602c92",
			"slotId": "main",
			"location": {
				"x": 1,
				"y": 0,
				"r": 0
			}
		},
		{
			"_id": "5e3829fa2855471525602c95",
			"_tpl": "573475fb24597737fb1379e1",
			"parentId": "5e3829fa2855471525602c92",
			"slotId": "main",
			"location": {
				"x": 3,
				"y": 0,
				"r": 0
			}
		}
	]
}