{
	"Id": "Lootable_00445",
	"IsStatic": true,
	"useGravity": true,
	"randomRotation": false,
	"Position": {
		"x": 0,
		"y": 0,
		"z": 0
	},
	"Rotation": {
		"x": 0,
		"y": 0,
		"z": 0
	},
	"IsGroupPosition": false,
	"GroupPositions": [],
	"Root": "5e382a211d55576e1a5277fe",
	"Items": [
		{
			"_id": "5e382a211d55576e1a5277fe",
			"_tpl": "5909d50c86f774659e6aaebe"
		},
		{
			"_id": "5e382a211d55576e1a5277ff",
			"_tpl": "590c2c9c86f774245b1f03f2",
			"parentId": "5e382a211d55576e1a5277fe",
			"slotId": "main",
			"location": {
				"x": 0,
				"y": 0,
				"r": 0
			}
		},
		{
			"_id": "5e382a211d55576e1a527800",
			"_tpl": "590c2c9c86f774245b1f03f2",
			"parentId": "5e382a211d55576e1a5277fe",
			"slotId": "main",
			"location": {
				"x": 1,
				"y": 0,
				"r": 0
			}
		}
	]
}