{
	"Id": "loot_ammo_common (31)3928342",
	"IsStatic": false,
	"useGravity": true,
	"randomRotation": true,
	"Position": {
		"x": 68.03302,
		"y": -0.095,
		"z": -165.090973
	},
	"Rotation": {
		"x": 0,
		"y": 0,
		"z": 0
	},
	"IsGroupPosition": false,
	"GroupPositions": [],
	"Root": "5e382a10ecfb65468500d962",
	"Items": [
		{
			"_id": "5e382a10ecfb65468500d962",
			"_tpl": "57372c21245977670937c6c2"
		},
		{
			"_id": "5e382a10ecfb65468500d963",
			"_tpl": "56dff061d2720bb5668b4567",
			"parentId": "5e382a10ecfb65468500d962",
			"slotId": "cartridges",
			"upd": {
				"StackObjectsCount": 60
			}
		},
		{
			"_id": "5e382a10ecfb65468500d964",
			"_tpl": "56dff061d2720bb5668b4567",
			"parentId": "5e382a10ecfb65468500d962",
			"slotId": "cartridges",
			"location": 1,
			"upd": {
				"StackObjectsCount": 60
			}
		}
	]
}