{
	"Id": "loot_rf_ammo_true (61)3937328",
	"IsStatic": false,
	"useGravity": true,
	"randomRotation": true,
	"Position": {
		"x": -103.089294,
		"y": -2.92099977,
		"z": 95.32361
	},
	"Rotation": {
		"x": 0,
		"y": 0,
		"z": 0
	},
	"IsGroupPosition": false,
	"GroupPositions": [],
	"Root": "5e382a2468b10c71c31135ad",
	"Items": [
		{
			"_id": "5e382a2468b10c71c31135ad",
			"_tpl": "5737250c2459776125652acc"
		},
		{
			"_id": "5e382a2468b10c71c31135ae",
			"_tpl": "573719df2459775a626ccbc2",
			"parentId": "5e382a2468b10c71c31135ad",
			"slotId": "cartridges",
			"upd": {
				"StackObjectsCount": 16
			}
		}
	]
}