{
	"Id": "Lootable_00090",
	"IsStatic": true,
	"useGravity": true,
	"randomRotation": false,
	"Position": {
		"x": 0,
		"y": 0,
		"z": 0
	},
	"Rotation": {
		"x": 0,
		"y": 0,
		"z": 0
	},
	"IsGroupPosition": false,
	"GroupPositions": [],
	"Root": "5e382a2868b10c71c3113a3b",
	"Items": [
		{
			"_id": "5e382a2868b10c71c3113a3b",
			"_tpl": "578f87b7245977356274f2cd"
		},
		{
			"_id": "5e382a2868b10c71c3113a3c",
			"_tpl": "56742c284bdc2d98058b456d",
			"parentId": "5e382a2868b10c71c3113a3b",
			"slotId": "main",
			"location": {
				"x": 0,
				"y": 0,
				"r": 0
			}
		},
		{
			"_id": "5e382a2868b10c71c3113a3d",
			"_tpl": "5734795124597738002c6176",
			"parentId": "5e382a2868b10c71c3113a3b",
			"slotId": "main",
			"location": {
				"x": 1,
				"y": 0,
				"r": 0
			}
		}
	]
}