{
	"Id": "loot_ammo_rus (6)3923834",
	"IsStatic": false,
	"useGravity": true,
	"randomRotation": true,
	"Position": {
		"x": 2.86157227,
		"y": -6.360081,
		"z": -16.6985779
	},
	"Rotation": {
		"x": 0,
		"y": 0,
		"z": 0
	},
	"IsGroupPosition": false,
	"GroupPositions": [],
	"Root": "5e382a2468b10c71c311334a",
	"Items": [
		{
			"_id": "5e382a2468b10c71c311334a",
			"_tpl": "57372c89245977685d4159b1"
		},
		{
			"_id": "5e382a2468b10c71c311334b",
			"_tpl": "56dff061d2720bb5668b4567",
			"parentId": "5e382a2468b10c71c311334a",
			"slotId": "cartridges",
			"upd": {
				"StackObjectsCount": 30
			}
		}
	]
}