{
	"Id": "GunsafeSpawn 1 (1)(Clone)3924110",
	"IsStatic": false,
	"useGravity": true,
	"randomRotation": false,
	"Position": {
		"x": -39.5440674,
		"y": 18.749094,
		"z": 169.4809
	},
	"Rotation": {
		"x": 270,
		"y": 272.058075,
		"z": 0
	},
	"IsGroupPosition": false,
	"GroupPositions": [],
	"Root": "5e382a10ecfb65468500d927",
	"Items": [
		{
			"_id": "5e382a10ecfb65468500d927",
			"_tpl": "5739d41224597779c3645501"
		},
		{
			"_id": "5e382a10ecfb65468500d928",
			"_tpl": "56d59d3ad2720bdb418b4577",
			"parentId": "5e382a10ecfb65468500d927",
			"slotId": "cartridges",
			"upd": {
				"StackObjectsCount": 16
			}
		}
	]
}