{
	"Id": "Lootable_00431",
	"IsStatic": true,
	"useGravity": true,
	"randomRotation": false,
	"Position": {
		"x": 0,
		"y": 0,
		"z": 0
	},
	"Rotation": {
		"x": 0,
		"y": 0,
		"z": 0
	},
	"IsGroupPosition": false,
	"GroupPositions": [],
	"Root": "5e3829fb2855471525602dab",
	"Items": [
		{
			"_id": "5e3829fb2855471525602dab",
			"_tpl": "5909d5ef86f77467974efbd8"
		},
		{
			"_id": "5e3829fc2855471525602dac",
			"_tpl": "588226ef24597767af46e39c",
			"parentId": "5e3829fb2855471525602dab",
			"slotId": "main",
			"location": {
				"x": 0,
				"y": 0,
				"r": 0
			}
		},
		{
			"_id": "5e3829fc2855471525602dad",
			"_tpl": "57ffaea724597779f52b3a4d",
			"parentId": "5e3829fb2855471525602dab",
			"slotId": "main",
			"location": {
				"x": 1,
				"y": 0,
				"r": 0
			}
		}
	]
}